setup.py
pyexpression/__init__.py
pyexpression/expressions.py
pyexpression/ifexp.py
pyexpression.egg-info/PKG-INFO
pyexpression.egg-info/SOURCES.txt
pyexpression.egg-info/dependency_links.txt
pyexpression.egg-info/top_level.txt
test/test_expression.py
test/test_if.py