Metadata-Version: 1.0
Name: pyexpression
Version: 0.1.0
Summary: boost.lambda like function generator
Home-page: https://github.com/shomah4a/pyexpression
Author: Shoma Hosaka
Author-email: shoma.h4a+pypi@gmail.com
License: LGPL
Platform: UNKNOWN
Classifier: Programming Language :: Python
Classifier: Development Status :: 2 - Pre-Alpha
Classifier: License :: OSI Approved :: GNU Library or Lesser General Public License (LGPL)
Classifier: Programming Language :: Python :: 2
Classifier: Programming Language :: Python :: 2.6
Classifier: Programming Language :: Python :: 2.7
Classifier: Topic :: Software Development :: Libraries :: Python Modules
Classifier: Topic :: Utilities
